{
  "phase": "02",
  "nom": "NAVBAR & FOOTER",
  "description": "Création de la navigation principale avec scroll spy et du footer réutilisable",
  "objectif": "Implémenter une navbar moderne avec détection automatique de section active et footer professionnel",
  
  "prerequis": [
    "Phase 01 validée et app qui démarre",
    "Variables SCSS en place (_variables.scss)",
    "Mixins SCSS disponibles (_mixins.scss)"
  ],
  
  "proposition_design": {
    "titre": "💡 PROPOSITION DESIGN - Navigation Moderne",
    "ameliorations": [
      {
        "nom": "Navbar sticky avec backdrop blur",
        "description": "Navbar fixe en haut avec effet glassmorphism au scroll",
        "benefice": "Look moderne et professionnel, meilleure lisibilité",
        "css": "backdrop-filter: blur(10px); background: rgba(255,255,255,0.9);"
      },
      {
        "nom": "Transitions fluides liens actifs",
        "description": "Indicateur visuel animé sous le lien actif",
        "benefice": "Feedback visuel élégant pour l'utilisateur",
        "css": "border-bottom avec transition 0.3s"
      },
      {
        "nom": "Hamburger menu responsive",
        "description": "Menu mobile avec animation slide-in",
        "benefice": "Expérience mobile optimale",
        "css": "transform: translateX() avec transition"
      }
    ],
    "validation_requise": "Attendre validation avant implémentation"
  },
  
  "fichiers": [
    {
      "ordre": 1,
      "nom": "scroll-spy.service.ts",
      "path": "frontend/src/app/core/services/scroll-spy.service.ts",
      "type": "Service",
      "description": "Service qui détecte quelle section est visible à l'écran",
      "responsabilites": [
        "Observer les sections avec IntersectionObserver",
        "Détecter section >= 50% visible",
        "Émettre signal avec section active",
        "Update fragment dans Router"
      ],
      "technologie": "IntersectionObserver API + Signals",
      "instructions": [
        "Créer signal activeSection = signal<string>('hero')",
        "Méthode observe(sections: Element[])",
        "IntersectionObserver avec threshold 0.5",
        "Callback update activeSection()",
        "Cleanup sur destroy (unobserve)",
        "Injectable providedIn: 'root'",
        "Injection Router avec inject()",
        "Typage strict (aucun any)"
      ],
      "exemple_usage": "scrollSpyService.activeSection() → 'services'"
    },
    
    {
      "ordre": 2,
      "nom": "navbar.ts",
      "path": "frontend/src/app/shared/components/navbar/navbar.ts",
      "type": "Component",
      "description": "Composant navbar avec liens navigation et scroll spy",
      "structure": {
        "selector": "app-navbar",
        "standalone": true,
        "imports": ["RouterLink", "RouterLinkActive", "CommonModule"],
        "template": "navbar.html",
        "styles": "navbar.scss"
      },
      "logique": [
        "Injection ScrollSpyService avec inject()",
        "Signal isMenuOpen = signal(false)",
        "Signal activeSection depuis ScrollSpyService",
        "Méthode toggleMenu()",
        "Méthode closeMenu() (au clic sur lien)",
        "Effet sticky au scroll (détection dans template ou service)"
      ],
      "liens_navigation": [
        { "label": "Accueil", "fragment": "hero" },
        { "label": "Services", "fragment": "services" },
        { "label": "Tarifs", "fragment": "tarifs" },
        { "label": "Contact", "route": "/contact" }
      ],
      "instructions": [
        "Utiliser inject() pour injections",
        "Standalone component",
        "RouterLink avec [routerLink] et fragment",
        "RouterLinkActive pour active state",
        "Signal pour menu mobile (isMenuOpen)",
        "Hamburger button avec @if()",
        "Logo cliquable vers home",
        "Typage strict, aucun any"
      ]
    },
    
    {
      "ordre": 3,
      "nom": "navbar.html",
      "path": "frontend/src/app/shared/components/navbar/navbar.html",
      "type": "Template",
      "description": "Template de la navbar avec navigation responsive",
      "structure": [
        "<nav class='navbar'>",
        "  <div class='container'>",
        "    <a [routerLink]=\"['/']\" class='logo'>Plan & Co</a>",
        "    <ul class='nav-links' [class.open]='isMenuOpen()'>",
        "      <li><a [routerLink]=\"['/']\" fragment='hero'>Accueil</a></li>",
        "      <li><a [routerLink]=\"['/']\" fragment='services'>Services</a></li>",
        "      <li><a [routerLink]=\"['/']\" fragment='tarifs'>Tarifs</a></li>",
        "      <li><a [routerLink]=\"['/contact']\">Contact</a></li>",
        "    </ul>",
        "    <button class='hamburger' (click)='toggleMenu()'>",
        "      @if (isMenuOpen()) { ✕ } @else { ☰ }",
        "    </button>",
        "  </div>",
        "</nav>"
      ],
      "instructions": [
        "Utiliser RouterLink Angular (pas href)",
        "Fragment pour scroll vers sections",
        "Binding [class.open] pour menu mobile",
        "Event (click) pour hamburger",
        "Control flow @if pour icon hamburger",
        "Classes BEM ou cohérentes",
        "Sémantique HTML5 (<nav>, <ul>, <li>)"
      ]
    },
    
    {
      "ordre": 4,
      "nom": "navbar.scss",
      "path": "frontend/src/app/shared/components/navbar/navbar.scss",
      "type": "Styles",
      "description": "Styles de la navbar (sticky, responsive, animations)",
      "imports": [
        "@use '@assets/styles/variables' as *;",
        "@use '@assets/styles/mixins' as *;"
      ],
      "features_styles": [
        "Position sticky top 0",
        "Background blanc avec shadow",
        "Effet backdrop-filter blur (si validé)",
        "Transition smooth au scroll",
        "Links avec hover effects",
        "Active link avec border-bottom orange",
        "Responsive (breakpoint 768px)",
        "Menu mobile slide-in de droite",
        "Hamburger icon animé",
        "Z-index élevé (100)"
      ],
      "instructions": [
        "Utiliser variables SCSS ($primary-color, $spacing-md...)",
        "Mixin @include container si disponible",
        "Mobile-first ou desktop-first (cohérent)",
        "Transitions fluides (0.3s ease)",
        "Active state visible (border ou background)",
        "Hover effects subtiles",
        "Code propre et commenté"
      ]
    },
    
    {
      "ordre": 5,
      "nom": "footer.ts",
      "path": "frontend/src/app/shared/components/footer/footer.ts",
      "type": "Component",
      "description": "Composant footer réutilisable avec infos contact et liens",
      "structure": {
        "selector": "app-footer",
        "standalone": true,
        "imports": ["RouterLink"],
        "template": "footer.html",
        "styles": "footer.scss"
      },
      "logique": [
        "Composant simple (pas de logique complexe)",
        "Année dynamique: currentYear = new Date().getFullYear()",
        "Liens réseaux sociaux (si applicable)",
        "Email et téléphone cliquables"
      ],
      "instructions": [
        "Standalone component",
        "Signal ou variable pour currentYear",
        "RouterLink pour navigation interne",
        "Liens mailto: et tel: pour contact",
        "Minimal, pas de surcharge",
        "Typage strict"
      ]
    },
    
    {
      "ordre": 6,
      "nom": "footer.html",
      "path": "frontend/src/app/shared/components/footer/footer.html",
      "type": "Template",
      "description": "Template du footer avec colonnes info, navigation, contact",
      "structure": [
        "<footer class='footer'>",
        "  <div class='container'>",
        "    <div class='footer-grid'>",
        "      <div class='footer-col'>",
        "        <h3>Plan & Co</h3>",
        "        <p>Expert en copywriting et rédaction web.</p>",
        "      </div>",
        "      <div class='footer-col'>",
        "        <h4>Navigation</h4>",
        "        <ul>",
        "          <li><a [routerLink]=\"['/']\" fragment='services'>Services</a></li>",
        "          <li><a [routerLink]=\"['/contact']\">Contact</a></li>",
        "        </ul>",
        "      </div>",
        "      <div class='footer-col'>",
        "        <h4>Contact</h4>",
        "        <ul>",
        "          <li><a href='mailto:planandco9@gmail.com'>Email</a></li>",
        "          <li><a href='tel:0640286297'>Téléphone</a></li>",
        "        </ul>",
        "      </div>",
        "    </div>",
        "    <div class='footer-bottom'>",
        "      <p>&copy; {{ currentYear }} Plan & Co - Tous droits réservés</p>",
        "    </div>",
        "  </div>",
        "</footer>"
      ],
      "instructions": [
        "Grid responsive 3 colonnes (desktop) → 1 colonne (mobile)",
        "RouterLink pour navigation interne",
        "mailto: et tel: pour liens contact",
        "Interpolation {{ currentYear }}",
        "Sémantique HTML5 (<footer>)",
        "Classes cohérentes"
      ]
    },
    
    {
      "ordre": 7,
      "nom": "footer.scss",
      "path": "frontend/src/app/shared/components/footer/footer.scss",
      "type": "Styles",
      "description": "Styles du footer (dark background, grid, responsive)",
      "imports": [
        "@use '@assets/styles/variables' as *;",
        "@use '@assets/styles/mixins' as *;"
      ],
      "features_styles": [
        "Background dark (#2C3E50 ou $text-dark)",
        "Couleur texte blanc/gris clair",
        "Grid 3 colonnes desktop, 1 mobile",
        "Spacing cohérent avec variables",
        "Links hover effect (couleur primaire)",
        "Footer bottom avec border-top",
        "Padding généreux (top/bottom)"
      ],
      "instructions": [
        "Utiliser variables couleurs",
        "Grid avec gap",
        "Media query pour mobile",
        "Hover effect sur links",
        "Alignement centré footer-bottom",
        "Code propre"
      ]
    },
    
    {
      "ordre": 8,
      "nom": "app.component.ts (UPDATE)",
      "path": "frontend/src/app/app.component.ts",
      "type": "Component Update",
      "description": "Ajouter imports Navbar et Footer dans AppComponent",
      "modifications": [
        "Importer Navbar et Footer",
        "Ajouter dans imports array"
      ],
      "instructions": [
        "Import { Navbar } from './shared/components/navbar/navbar'",
        "Import { Footer } from './shared/components/footer/footer'",
        "Ajouter Navbar, Footer dans imports: [RouterOutlet, Navbar, Footer]",
        "Pas de logique supplémentaire"
      ]
    },
    
    {
      "ordre": 9,
      "nom": "app.component.html (UPDATE)",
      "path": "frontend/src/app/app.component.html",
      "type": "Template Update",
      "description": "Ajouter navbar et footer dans template",
      "structure": [
        "<app-navbar />",
        "<router-outlet />",
        "<app-footer />"
      ],
      "instructions": [
        "Décommenter ou ajouter <app-navbar />",
        "Garder <router-outlet />",
        "Décommenter ou ajouter <app-footer />",
        "Ordre: navbar → outlet → footer",
        "Propre et minimal"
      ]
    }
  ],
  
  "validation_phase": {
    "criteres": [
      "Navbar affichée en haut de page",
      "Links fonctionnels (routerLink)",
      "Menu mobile responsive (hamburger)",
      "Footer affiché en bas",
      "Aucune erreur console",
      "Aucune erreur TypeScript",
      "Scroll spy détecte sections (à tester phase suivante)"
    ],
    "commandes_test": [
      "cd frontend",
      "ng serve",
      "Ouvrir http://localhost:4200",
      "Vérifier navbar + footer visibles",
      "Tester menu mobile (réduire écran)",
      "Cliquer liens navigation"
    ]
  },
  
  "notes_importantes": [
    "Scroll spy sera testable uniquement quand sections home existeront (phase 3)",
    "Pour l'instant, navbar affiche liens mais pas de sections à scroller",
    "Menu mobile doit fonctionner (toggle)",
    "Footer doit être visible en bas",
    "Respecter workflow: 1 fichier = 1 validation",
    "Proposer design moderne si validé en début de phase"
  ],
  
  "integration_app": {
    "fichiers_modifies": [
      "app.component.ts (ajout imports)",
      "app.component.html (ajout navbar/footer)"
    ],
    "nouveaux_composants": [
      "Navbar (shared/components/navbar/)",
      "Footer (shared/components/footer/)"
    ],
    "nouveau_service": [
      "ScrollSpyService (core/services/)"
    ]
  }
}